setup.cfg
setup.py
approxeng.holochassis.egg-info/PKG-INFO
approxeng.holochassis.egg-info/SOURCES.txt
approxeng.holochassis.egg-info/dependency_links.txt
approxeng.holochassis.egg-info/not-zip-safe
approxeng.holochassis.egg-info/requires.txt
approxeng.holochassis.egg-info/top_level.txt
approxeng/chassis/__init__.py
approxeng/chassis/drive.py
approxeng/chassis/dynamics.py
approxeng/chassis/simulation.py
approxeng/chassis/simulationplot.py
approxeng/chassis/util.py